lupro/HTTPengine.py
lupro/__init__.py
lupro/__version__.py
lupro/analyzesController.py
lupro/api.py
lupro/config.py
lupro/controller.py
lupro/hooks.py
lupro/publictool.py
lupro/typing.py
lupro/useragent.py
lupro-1.0.8.dist-info/LICENSE
lupro-1.0.8.dist-info/METADATA
lupro-1.0.8.dist-info/WHEEL
lupro-1.0.8.dist-info/top_level.txt
lupro-1.0.8.dist-info/RECORD
