Metadata-Version: 2.1
Name: lupro
Version: 1.0.8
Summary: Elegant reptile frame for python.
Home-page: https://github.com/luxuncang/lupro
Author: ShengXin Lu
Author-email: luxuncang@qq.com
License: MIT
Platform: all
Classifier: Intended Audience :: Developers
Classifier: Operating System :: OS Independent
Classifier: Natural Language :: Chinese (Simplified)
Classifier: Programming Language :: Python :: 3.5
Classifier: Programming Language :: Python :: 3.6
Classifier: Programming Language :: Python :: 3.7
Classifier: Programming Language :: Python :: 3.8
Classifier: Programming Language :: Python :: 3.9
Classifier: Programming Language :: Python :: 3.10
Classifier: Topic :: Software Development :: Libraries
Requires-Dist: gevent
Requires-Dist: requests
Requires-Dist: lxml
Requires-Dist: dtanys
Requires-Dist: decorator
Requires-Dist: chardet
Requires-Dist: parsel
Requires-Dist: httpx
